topsis/__init__.py
topsis/__main__.py
topsis_anubhav_102003551-1.0.0.dist-info/LICENSE.txt
topsis_anubhav_102003551-1.0.0.dist-info/METADATA
topsis_anubhav_102003551-1.0.0.dist-info/WHEEL
topsis_anubhav_102003551-1.0.0.dist-info/entry_points.txt
topsis_anubhav_102003551-1.0.0.dist-info/top_level.txt
topsis_anubhav_102003551-1.0.0.dist-info/RECORD
