Metadata-Version: 2.1
Name: topsis-anubhav-102003551
Version: 1.0.0
Summary: A Python package to find TOPSIS for multi-criteria decision analysis method
Home-page: https://github.com/anubhav3003/Calco-O-Topsis
Author: Anubhav Gupta
Author-email: agupta10_be20@thapar.edu
License: MIT
Keywords: UCS654,TIET
License-File: LICENSE.txt
Requires-Dist: pandas
Requires-Dist: tabulate
